pinscrape/__init__.py
pinscrape/_version.py
pinscrape/models.py
pinscrape/pinscrape.py
pinscrape/utils.py
pinscrape/v2.py
pinscrape-5.1.0.dist-info/licenses/LICENSE
pinscrape-5.1.0.dist-info/METADATA
pinscrape-5.1.0.dist-info/WHEEL
pinscrape-5.1.0.dist-info/top_level.txt
pinscrape-5.1.0.dist-info/RECORD
