Metadata-Version: 2.4
Name: pinscrape
Version: 5.1.0
Summary: Pinterest | a simple data scraper for pinterest
Home-page: https://github.com/iamatulsingh/pinscrape
Author: Atul Singh
Author-email: atulsingh0401@gmail.com
Classifier: Programming Language :: Python :: 3
Classifier: License :: OSI Approved :: MIT License
Classifier: Operating System :: OS Independent
Requires-Python: >=3.6
License-File: LICENSE
Requires-Dist: pytest==7.2.0
Requires-Dist: requests~=2.32.4
Requires-Dist: beautifulsoup4==4.13.4
Requires-Dist: pydotmap~=0.1.3
Requires-Dist: opencv-python~=4.11.0.86
Requires-Dist: numpy~=2.3.1
Requires-Dist: pydantic~=2.10.3
Dynamic: author
Dynamic: author-email
Dynamic: classifier
Dynamic: description
Dynamic: description-content-type
Dynamic: home-page
Dynamic: license-file
Dynamic: requires-dist
Dynamic: requires-python
Dynamic: summary
